cementstarter/__init__.py
cementstarter/bootstrap.py
cementstarter/main.py
cementstarter/controllers/__init__.py
cementstarter/controllers/base.py
cementstarter/core/__init__.py
cementstarter/core/exc.py
cementstarter/core/version.py
cementstarter/ext/__init__.py
cementstarter/plugins/__init__.py
cementstarter/templates/__init__.py
cementstarter/templates/command1.jinja2
cementstarter-0.0.1.dist-info/LICENSE.md
cementstarter-0.0.1.dist-info/METADATA
cementstarter-0.0.1.dist-info/WHEEL
cementstarter-0.0.1.dist-info/entry_points.txt
cementstarter-0.0.1.dist-info/top_level.txt
cementstarter-0.0.1.dist-info/RECORD
