Metadata-Version: 2.1
Name: cementstarter
Version: 0.0.1
Summary: A cement boilerplate
Home-page: https://github.com/johndoe/myapp/
Author: create email
Author-email: john.doe@example.com
License: unlicensed
Platform: UNKNOWN
